hero_key_env/__init__.py
hero_key_env/hero_key_env/__init__.py
hero_key_env/hero_key_env/actions.py
hero_key_env/hero_key_env/hero_key_env.py
hero_key_env/hero_key_env/status.py
hero_key_env/hero_key_env/infer/__init__.py
hero_key_env/hero_key_env/infer/model/__init__.py
hero_key_env/hero_key_env/infer/python/__init__.py
hero_key_env/hero_key_env/infer/python/benchmark_utils.py
hero_key_env/hero_key_env/infer/python/det_keypoint_unite_infer.py
hero_key_env/hero_key_env/infer/python/det_keypoint_unite_utils.py
hero_key_env/hero_key_env/infer/python/infer.py
hero_key_env/hero_key_env/infer/python/keypoint_infer.py
hero_key_env/hero_key_env/infer/python/keypoint_postprocess.py
hero_key_env/hero_key_env/infer/python/keypoint_preprocess.py
hero_key_env/hero_key_env/infer/python/mot_jde_infer.py
hero_key_env/hero_key_env/infer/python/mot_keypoint_unite_infer.py
hero_key_env/hero_key_env/infer/python/mot_keypoint_unite_utils.py
hero_key_env/hero_key_env/infer/python/mot_sde_infer.py
hero_key_env/hero_key_env/infer/python/picodet_postprocess.py
hero_key_env/hero_key_env/infer/python/preprocess.py
hero_key_env/hero_key_env/infer/python/utils.py
hero_key_env/hero_key_env/infer/python/visualize.py
hero_key_env-0.0.3.dist-info/METADATA
hero_key_env-0.0.3.dist-info/WHEEL
hero_key_env-0.0.3.dist-info/top_level.txt
hero_key_env-0.0.3.dist-info/RECORD
