Metadata-Version: 2.1
Name: hero-key-env
Version: 0.0.3
Summary: test
Requires-Dist: gym
